{
  "users": [
    {
      "name": "Lucky yadav",
      "email": "luckyyadav8627@gmail.com",
      "password": "hv n",
      "token": null,
      "id": 1
    },
    {
      "name": "Lucky yadav",
      "email": "luckyyadav8627@gmail.com",
      "password": "edrfgthyn",
      "number": "+919499370283",
      "token": "",
      "id": 2
    },
    {
      "name": "Lucky yadav",
      "email": "luckyyadav8627@gmail.com",
      "password": "gjbn ",
      "number": "+919485949413",
      "token": "",
      "id": 3
    }
  ]
  // json-server -p 4000 Lucky.json
}

